silly_pyproject_name/__init__.py
silly_pyproject_name/__main__.py
silly_pyproject_name/git.py
silly_pyproject_name/name.py
silly_pyproject_name/tests/__init__.py
silly_pyproject_name/tests/test_init.py
silly_pyproject_name-2024.1.19.76487.dev1.dist-info/METADATA
silly_pyproject_name-2024.1.19.76487.dev1.dist-info/WHEEL
silly_pyproject_name-2024.1.19.76487.dev1.dist-info/entry_points.txt
silly_pyproject_name-2024.1.19.76487.dev1.dist-info/top_level.txt
silly_pyproject_name-2024.1.19.76487.dev1.dist-info/RECORD
