Metadata-Version: 2.1
Name: silly_pyproject_name
Version: 2024.1.19.76487.dev1
Summary: CLI tools for manipulating Python project's name. Example for Gather.
Author-email: Moshe Zadka <moshez@zadka.club>
License: Permission is hereby granted, free of charge, to any person obtaining a
Project-URL: Homepage, https://github.com/elcaminoreal/silly_pyproject_name
Provides-Extra: doc
Requires-Dist: sphinx ; extra == 'doc'
Provides-Extra: docs
Requires-Dist: sphinx ; extra == 'docs'
Provides-Extra: lint
Requires-Dist: flake8 ; extra == 'lint'
Requires-Dist: black ; extra == 'lint'
Provides-Extra: mypy
Requires-Dist: mypy ; extra == 'mypy'
Provides-Extra: test
Requires-Dist: coverage ; extra == 'test'
Requires-Dist: virtue ; extra == 'test'
Provides-Extra: tests
Requires-Dist: virtue ; extra == 'tests'
Requires-Dist: pyhamcrest ; extra == 'tests'
Requires-Dist: coverage ; extra == 'tests'
